test_fastuuid-0.9.1.dist-info/METADATA
test_fastuuid-0.9.1.dist-info/WHEEL
test_fastuuid-0.9.1.dist-info/license_files/LICENSE
fastuuid/__init__.py
fastuuid/__init__.pyi
fastuuid/py.typed
fastuuid/fastuuid.cpython-37m-x86_64-linux-gnu.so
test_fastuuid-0.9.1.dist-info/RECORD
