Metadata-Version: 2.3
Name: test_fastuuid
Version: 0.9.1
License-File: LICENSE
Summary: Python bindings to Rust's UUID library.
Author: Omer Katz <omer.drow@gmail.com>
Author-email: Omer Katz <omer.drow@gmail.com>
License: BSD3
Requires-Python: >=3.7
